mlblocks/__init__.py
mlblocks/discovery.py
mlblocks/mlblock.py
mlblocks/mlpipeline.py
mlblocks-0.6.2.dist-info/AUTHORS.rst
mlblocks-0.6.2.dist-info/LICENSE
mlblocks-0.6.2.dist-info/METADATA
mlblocks-0.6.2.dist-info/WHEEL
mlblocks-0.6.2.dist-info/top_level.txt
mlblocks-0.6.2.dist-info/RECORD
