Metadata-Version: 2.1
Name: mlblocks
Version: 0.6.2
Summary: Pipelines and primitives for machine learning and data science.
Home-page: https://github.com/MLBazaar/MLBlocks
Author: MIT Data To AI Lab
Author-email: dailabmit@gmail.com
License: MIT license
Keywords: auto machine learning classification regression data science pipeline
Classifier: Development Status :: 2 - Pre-Alpha
Classifier: Intended Audience :: Developers
Classifier: License :: OSI Approved :: MIT License
Classifier: Natural Language :: English
Classifier: Programming Language :: Python :: 3
Classifier: Programming Language :: Python :: 3.8
Classifier: Programming Language :: Python :: 3.9
Classifier: Programming Language :: Python :: 3.10
Classifier: Programming Language :: Python :: 3.11
Classifier: Programming Language :: Python :: 3.12
Classifier: Programming Language :: Python :: 3.13
Requires-Python: >=3.8,<3.14
License-File: LICENSE
License-File: AUTHORS.rst
Requires-Dist: graphviz<1,>=0.9
Requires-Dist: numpy<3,>=1.17.1
Requires-Dist: psutil<7,>=5
Provides-Extra: dev
Requires-Dist: bumpversion<0.6,>=0.5.3; extra == "dev"
Requires-Dist: pip>=9.0.1; extra == "dev"
Requires-Dist: watchdog<5,>=0.8.3; extra == "dev"
Requires-Dist: m2r<0.3,>=0.2.0; extra == "dev"
Requires-Dist: Sphinx<3,>=1.7.1; extra == "dev"
Requires-Dist: sphinx-rtd-theme<0.5,>=0.2.4; extra == "dev"
Requires-Dist: docutils<0.18,>=0.12; extra == "dev"
Requires-Dist: ipython>=6.5.0; extra == "dev"
Requires-Dist: autodocsumm>=0.1.10; extra == "dev"
Requires-Dist: Jinja2<3,>=2; extra == "dev"
Requires-Dist: markupsafe<2.1.0; extra == "dev"
Requires-Dist: alabaster<=0.7.12; extra == "dev"
Requires-Dist: sphinxcontrib-applehelp<1.0.8; extra == "dev"
Requires-Dist: sphinxcontrib-devhelp<1.0.6; extra == "dev"
Requires-Dist: sphinxcontrib-htmlhelp<2.0.5; extra == "dev"
Requires-Dist: sphinxcontrib-serializinghtml<1.1.10; extra == "dev"
Requires-Dist: sphinxcontrib-qthelp<1.0.7; extra == "dev"
Requires-Dist: flake8<4,>=3.7.7; extra == "dev"
Requires-Dist: isort<5,>=4.3.4; extra == "dev"
Requires-Dist: autoflake<2,>=1.1; extra == "dev"
Requires-Dist: autopep8<2,>=1.4.3; extra == "dev"
Requires-Dist: twine<4,>=1.10.0; extra == "dev"
Requires-Dist: wheel>=0.30.0; extra == "dev"
Requires-Dist: coverage<6,>=4.5.1; extra == "dev"
Requires-Dist: tox<4,>=2.9.1; extra == "dev"
Requires-Dist: doc8>=0.8.0; extra == "dev"
Requires-Dist: pydocstyle>=3.0.0; extra == "dev"
Requires-Dist: pytest>=3.4.2; extra == "dev"
Requires-Dist: pytest-cov>=2.6.0; extra == "dev"
Requires-Dist: setuptools>=41.0.0; extra == "dev"
Requires-Dist: rundoc>=0.4.3; extra == "dev"
Requires-Dist: prompt-toolkit<3.0,>=2.0; extra == "dev"
Requires-Dist: mlprimitives<0.5,>=0.4.0; extra == "dev"
Requires-Dist: h5py<4,>=2.10.0; extra == "dev"
Requires-Dist: matplotlib<4,>=2.2.2; extra == "dev"
Requires-Dist: protobuf<4; extra == "dev"
Requires-Dist: jupyter==1.0.0; extra == "dev"
Requires-Dist: baytune<0.6,>=0.5.0; extra == "dev"
Requires-Dist: copulas<0.12; extra == "dev"
Provides-Extra: examples
Requires-Dist: mlprimitives<0.5,>=0.4.0; extra == "examples"
Requires-Dist: h5py<4,>=2.10.0; extra == "examples"
Requires-Dist: matplotlib<4,>=2.2.2; extra == "examples"
Requires-Dist: protobuf<4; extra == "examples"
Requires-Dist: jupyter==1.0.0; extra == "examples"
Requires-Dist: baytune<0.6,>=0.5.0; extra == "examples"
Requires-Dist: copulas<0.12; extra == "examples"
Provides-Extra: mlprimitives
Requires-Dist: mlprimitives<0.5,>=0.4.0; extra == "mlprimitives"
Requires-Dist: h5py<4,>=2.10.0; extra == "mlprimitives"
Requires-Dist: matplotlib<4,>=2.2.2; extra == "mlprimitives"
Requires-Dist: protobuf<4; extra == "mlprimitives"
Provides-Extra: test
Requires-Dist: pytest>=3.4.2; extra == "test"
Requires-Dist: pytest-cov>=2.6.0; extra == "test"
Requires-Dist: setuptools>=41.0.0; extra == "test"
Requires-Dist: rundoc>=0.4.3; extra == "test"
Requires-Dist: prompt-toolkit<3.0,>=2.0; extra == "test"
Requires-Dist: mlprimitives<0.5,>=0.4.0; extra == "test"
Requires-Dist: h5py<4,>=2.10.0; extra == "test"
Requires-Dist: matplotlib<4,>=2.2.2; extra == "test"
Requires-Dist: protobuf<4; extra == "test"
Requires-Dist: jupyter==1.0.0; extra == "test"
Requires-Dist: baytune<0.6,>=0.5.0; extra == "test"
Requires-Dist: copulas<0.12; extra == "test"
Provides-Extra: unit
Requires-Dist: pytest>=3.4.2; extra == "unit"
Requires-Dist: pytest-cov>=2.6.0; extra == "unit"
Requires-Dist: setuptools>=41.0.0; extra == "unit"
Requires-Dist: rundoc>=0.4.3; extra == "unit"
Requires-Dist: prompt-toolkit<3.0,>=2.0; extra == "unit"
